README.md
setup.cfg
setup.py
asynctoolspy/__init__.py
asynctoolspy/appoint_tool.py
asynctoolspy/asynciter_tool.py
asynctoolspy.egg-info/PKG-INFO
asynctoolspy.egg-info/SOURCES.txt
asynctoolspy.egg-info/dependency_links.txt
asynctoolspy.egg-info/top_level.txt