Metadata-Version: 2.4
Name: asynctoolspy
Version: 1.2
Summary: asynctoolspy is a set of simple tools to speed up Python async development. It includes the appoint_limit_async decorator to limit how often an async function can be called by setting max attempts and intervals, useful for APIs with rate limits. The decorator handles errors with retries and pauses to improve reliability. It also features AsyncIterWrapper, an async iterator supporting optional delays and sync/async callbacks for flexible data processing.
Home-page: https://gitlab.com/asurnovsurnov/asynctoolspy/
Author: Aleksei Surnov
Author-email: asurnovsurnov@gmail.com
Classifier: Programming Language :: Python :: 3
Classifier: Operating System :: OS Independent
Requires-Python: >=3.8
Dynamic: author
Dynamic: author-email
Dynamic: classifier
Dynamic: description
Dynamic: description-content-type
Dynamic: home-page
Dynamic: requires-python
Dynamic: summary
